tabulairity/__init__.py
tabulairity/gsheetconnector.py
tabulairity/scrapertools.py
tabulairity/selfimprovement.py
tabulairity/tabulairity.py
tabulairity-1.1.0.dist-info/licenses/LICENSE
tabulairity-1.1.0.dist-info/METADATA
tabulairity-1.1.0.dist-info/WHEEL
tabulairity-1.1.0.dist-info/top_level.txt
tabulairity-1.1.0.dist-info/RECORD
