Metadata-Version: 2.4
Name: TabulAIrity
Version: 1.1.0
Summary: Chat network based interrogation of unstructured text
Author-email: James Schlitt <schlittdatasci@gmail.com>
Project-URL: Homepage, https://github.com/SchlittDataSci/TabulAIrity
Project-URL: Issues, https://github.com/SchlittDataSci/TabulAIrity/issues
Classifier: Programming Language :: Python :: 3
Classifier: License :: OSI Approved :: GNU General Public License v3 or later (GPLv3+)
Classifier: Operating System :: OS Independent
Requires-Python: >=3.8
License-File: LICENSE
Dynamic: license-file
